odoo/addons/pos_display_total_quantity/README.rst
odoo/addons/pos_display_total_quantity/__init__.py
odoo/addons/pos_display_total_quantity/__manifest__.py
odoo/addons/pos_display_total_quantity/i18n/fr.po
odoo/addons/pos_display_total_quantity/i18n/fr_CH.po
odoo/addons/pos_display_total_quantity/i18n/it.po
odoo/addons/pos_display_total_quantity/i18n/pos_display_total_quantity.pot
odoo/addons/pos_display_total_quantity/readme/CONTRIBUTORS.md
odoo/addons/pos_display_total_quantity/readme/CREDITS.md
odoo/addons/pos_display_total_quantity/readme/DESCRIPTION.md
odoo/addons/pos_display_total_quantity/static/description/icon.png
odoo/addons/pos_display_total_quantity/static/description/index.html
odoo/addons/pos_display_total_quantity/static/src/js/overrides/screens/order_summary/order_summary.esm.js
odoo/addons/pos_display_total_quantity/static/src/xml/pos_display_total_quantity.xml
odoo/addons/pos_display_total_quantity/static/tests/tours/DisplayTotal.tour.esm.js
odoo/addons/pos_display_total_quantity/tests/__init__.py
odoo/addons/pos_display_total_quantity/tests/test_frontend.py
odoo_addon_pos_display_total_quantity-18.0.1.0.0.8.dist-info/METADATA
odoo_addon_pos_display_total_quantity-18.0.1.0.0.8.dist-info/WHEEL
odoo_addon_pos_display_total_quantity-18.0.1.0.0.8.dist-info/top_level.txt
odoo_addon_pos_display_total_quantity-18.0.1.0.0.8.dist-info/RECORD
